mynhanes/.coverage
mynhanes/__init__.py
mynhanes/cli_entry.py
mynhanes/conftest.py
mynhanes/core/__init__.py
mynhanes/core/asgi.py
mynhanes/core/parameters.py
mynhanes/core/parameters.yml
mynhanes/core/settings.py
mynhanes/core/urls.py
mynhanes/core/wsgi.py
mynhanes/manage.py
mynhanes/masterdata/cycles.csv
mynhanes/masterdata/dataset_cycles.csv
mynhanes/masterdata/datasets.csv
mynhanes/masterdata/groups.csv
mynhanes/masterdata/query_columns.csv
mynhanes/masterdata/rule_variables.csv
mynhanes/masterdata/rules.csv
mynhanes/masterdata/tags.csv
mynhanes/masterdata/variable_cycles.csv
mynhanes/masterdata/variables.csv
mynhanes/masterdata/variables_tags.csv
mynhanes/masterdata/versions.csv
mynhanes/masterdata/work_process_master_data.csv
mynhanes/masterdata/work_process_rule.csv
mynhanes/masterdata/work_processes.csv
mynhanes/nhanes/__init__.py
mynhanes/nhanes/admin.py
mynhanes/nhanes/apps.py
mynhanes/nhanes/management/commands/clean_data.py
mynhanes/nhanes/management/commands/clean_logs.py
mynhanes/nhanes/management/commands/deploy.py
mynhanes/nhanes/management/commands/ingestion_nhanes.py
mynhanes/nhanes/management/commands/masterdata_export.py
mynhanes/nhanes/management/commands/masterdata_import.py
mynhanes/nhanes/management/commands/query.py
mynhanes/nhanes/management/commands/reset_transformation_data.py
mynhanes/nhanes/management/commands/sync_datasetcycle.py
mynhanes/nhanes/management/commands/sync_workprocess.py
mynhanes/nhanes/management/commands/transformation.py
mynhanes/nhanes/management/commands/update_variables_tags.py
mynhanes/nhanes/migrations/0001_initial.py
mynhanes/nhanes/migrations/0002_alter_cycle_options_alter_data_options_and_more.py
mynhanes/nhanes/migrations/0003_alter_variablecycle_unique_together.py
mynhanes/nhanes/migrations/0004_alter_rulevariable_dataset.py
mynhanes/nhanes/migrations/0005_alter_querycolumns_options_and_more.py
mynhanes/nhanes/migrations/0006_datasetcycle_observation.py
mynhanes-0.2.2.dist-info/LICENSE
mynhanes-0.2.2.dist-info/METADATA
mynhanes-0.2.2.dist-info/WHEEL
mynhanes-0.2.2.dist-info/entry_points.txt
mynhanes-0.2.2.dist-info/RECORD
