Metadata-Version: 2.1
Name: mynhanes
Version: 0.2.2
Summary: 
Author: Andre
Author-email: ricoandre@hotmail.com
Requires-Python: >=3.12,<4.0
Classifier: Programming Language :: Python :: 3
Classifier: Programming Language :: Python :: 3.12
Requires-Dist: bs4 (>=0.0.2,<0.0.3)
Requires-Dist: dask[distributed] (>=2024.8.0,<2025.0.0)
Requires-Dist: django (>=5.0.8,<6.0.0)
Requires-Dist: html5lib (>=1.1,<2.0)
Requires-Dist: jupyter (>=1.0.0,<2.0.0)
Requires-Dist: lxml (>=5.3.0,<6.0.0)
Requires-Dist: pandas (>=2.2.2,<3.0.0)
Requires-Dist: pyreadstat (>=1.2.7,<2.0.0)
Requires-Dist: pytest-django (>=4.8.0,<5.0.0)
Requires-Dist: requests (>=2.32.3,<3.0.0)
